.DS_Store
tissue_enrichment_analysis/__init__.py
tissue_enrichment_analysis/hypergeometricTests.py
tissue_enrichment_analysis-0.17.6.data/scripts/tea
tissue_enrichment_analysis-0.17.6.dist-info/DESCRIPTION.rst
tissue_enrichment_analysis-0.17.6.dist-info/METADATA
tissue_enrichment_analysis-0.17.6.dist-info/RECORD
tissue_enrichment_analysis-0.17.6.dist-info/WHEEL
tissue_enrichment_analysis-0.17.6.dist-info/metadata.json
tissue_enrichment_analysis-0.17.6.dist-info/top_level.txt
