Metadata-Version: 2.0
Name: tissue-enrichment-analysis
Version: 0.17.6
Summary: This package contains all the software used to implement  TEA in WormBase and remotely
Home-page: https://github.com/dangeles/TissueEnrichmentAnalysis
Author: David Angeles-Albores
Author-email: dangeles@caltech.edu
License: UNKNOWN
Download-URL: https://github.com/dangeles/TissueEnrichmentAnalysis/tarball/0.17.6
Keywords: tissue enrichment analysis,TEA,RNAseq,celegans,biology
Platform: UNKNOWN
Classifier: License :: OSI Approved :: MIT License
Classifier: Programming Language :: Python :: 3.5
Requires-Dist: matplotlib
Requires-Dist: scipy
Requires-Dist: numpy
Requires-Dist: pandas
Requires-Dist: seaborn
